dev/tailwind.css
retailwind/__init__.py
retailwind/__main__.py
retailwind/interactive.py
retailwind/parser.py
retailwind/tailwind.py
retailwind/translator.py
retailwind-0.1.0.dist-info/METADATA
retailwind-0.1.0.dist-info/WHEEL
retailwind-0.1.0.dist-info/entry_points.txt
retailwind-0.1.0.dist-info/RECORD
