Metadata-Version: 2.1
Name: retailwind
Version: 0.1.0
Summary: Reverse obfuscated tailwind classes
Home-page: https://github.com/asiffer/retailwind
License: MIT
Keywords: tailwind,reverse
Author: Alban Siffer
Author-email: alban.siffer@irisa.fr
Requires-Python: >=3.11,<4.0
Classifier: License :: OSI Approved :: MIT License
Classifier: Programming Language :: Python :: 3
Classifier: Programming Language :: Python :: 3.11
Requires-Dist: beautifulsoup4 (>=4.12.2,<5.0.0)
Requires-Dist: click (>=8.1.7,<9.0.0)
Requires-Dist: requests (>=2.31.0,<3.0.0)
Requires-Dist: rich (>=13.6.0,<14.0.0)
Requires-Dist: textual[syntax] (>=0.41.0,<0.42.0)
Project-URL: Repository, https://github.com/asiffer/retailwind
